config_fastapi/__init__.py
config_fastapi/config.py
config_fastapi/constants.py
config_fastapi/loaders.py
config_fastapi-1.0.0.dist-info/METADATA
config_fastapi-1.0.0.dist-info/WHEEL
config_fastapi-1.0.0.dist-info/RECORD
